{
    "$schema": "https://schema.management.azure.com/schemas/2015-01-01/deploymentParameters.json#",
    "contentVersion": "1.0.0.0",
  "parameters": {
    "applicationName": {
      "value": "gtw"
    },
    "environmentName": {
      "value": "dev"
    },
    "projectCoreRgName": {
      "value": "s141d01-3075"
    },
    "vnetName": {
      "value": "gateway-dev-vnet3075"
    },
    "subnetName": {
      "value": "snet3075"
    },
    "sslKeyVaultCertSecretId": {
      "value": "https://s141d01-signin-global-kv.vault.azure.net:443/secrets/non-prod-gateway"
    },
    "userAssignedIdentityName": {
      "value": "s141d01-dev-gtw-id"
    },
    "projectId": {
      "value": "s141"
    },
    "environmentId": {
      "value": "d01"
    },
    "hostName1": {
      "value": "oidc"
    },
    "hostName2": {
      "value": "interactions"
    },
    "domainSuffix": {
      "value": "education.gov.uk"
    },
    "project": {
      "value": "signin"
    },
    "isProduction": {
      "value": false
    }
  }
}